{"cameraMode":{"drawMode":0,"name":"Shaded","section":"Shading Mode"},"sceneLighting":false,"audioPlay":false,"sceneViewState":{"m_AlwaysRefresh":false,"showFog":true,"showSkybox":false,"showFlares":true,"showImageEffects":true,"showParticleSystems":true,"showVisualEffectGraphs":true,"m_FxEnabled":true},"in2DMode":false,"pivot":{"x":-0.47882747650146487,"y":21.317276000976564,"z":3.100393772125244},"rotation":{"x":-0.09063354134559632,"y":-0.678324282169342,"z":0.08488974720239639,"w":-0.724208414554596},"size":14.804781913757325,"orthographic":false}